setup.py
tdexApi/__init__.py
tdexApi.egg-info/PKG-INFO
tdexApi.egg-info/SOURCES.txt
tdexApi.egg-info/dependency_links.txt
tdexApi.egg-info/top_level.txt